{
  "questions": [
    {
      "id": "Q1",
      "marks": 1,
      "difficulty": "O'rta",
      "strand": "Raqamli fikrlash",
      "topic": "Sonli ketma-ketlik",
      "subTopic": "Algebraik fikrlash / qonuniyatlar",
      "skill": "Qonuniyatni aniqlash",
      "bloom": "Tahlil",
      "reasoning": "Induktiv",
      "gradeLevel": "10-sinf",
      "framework": "Cambridge Thinking Skills"
    },
    {
      "id": "Q2",
      "marks": 1,
      "difficulty": "Oson",
      "strand": "Deduktiv mantiq",
      "topic": "Mantiqiy tartiblash",
      "subTopic": "Deduktiv mantiq / tranzitivlik",
      "skill": "Mantiqiy xulosa chiqarish",
      "bloom": "Tahlil",
      "reasoning": "Deduktiv",
      "gradeLevel": "10-sinf",
      "framework": "Cambridge Thinking Skills"
    },
    {
      "id": "Q3",
      "marks": 1,
      "difficulty": "Oson",
      "strand": "Noverbal mulohaza",
      "topic": "Vizual qonuniyat (rasm)",
      "subTopic": "Noverbal mulohaza / fazoviy",
      "skill": "Aqliy aylantirish",
      "bloom": "Qo'llash",
      "reasoning": "Fazoviy",
      "gradeLevel": "10-sinf",
      "framework": "Cambridge Thinking Skills"
    },
    {
      "id": "Q4",
      "marks": 1,
      "difficulty": "Oson",
      "strand": "Ma'lumotlar tahlili",
      "topic": "Diagramma tahlili (rasm)",
      "subTopic": "Maʼlumotlar savodxonligi",
      "skill": "Maʼlumotni talqin qilish",
      "bloom": "Tahlil",
      "reasoning": "Analitik",
      "gradeLevel": "10-sinf",
      "framework": "Cambridge Thinking Skills"
    },
    {
      "id": "Q5",
      "marks": 1,
      "difficulty": "O'rta",
      "strand": "Tanqidiy mulohaza",
      "topic": "Tanqidiy fikrlash (ssenariy)",
      "subTopic": "Mantiqiy xatolar / sabab-natija",
      "skill": "Tanqidiy baholash",
      "bloom": "Baholash",
      "reasoning": "Analitik",
      "gradeLevel": "10-sinf",
      "framework": "Cambridge Thinking Skills"
    },
    {
      "id": "Q6",
      "marks": 1,
      "difficulty": "Qiyin",
      "strand": "Tanqidiy mulohaza",
      "topic": "Strategiya / optimallashtirish",
      "subTopic": "Algoritmik fikrlash",
      "skill": "Strategik fikrlash",
      "bloom": "Tahlil",
      "reasoning": "Deduktiv",
      "gradeLevel": "10-sinf",
      "framework": "Cambridge Thinking Skills"
    },
    {
      "id": "Q7",
      "marks": 1,
      "difficulty": "O'rta",
      "strand": "Deduktiv mantiq",
      "topic": "Mantiqiy jadval",
      "subTopic": "Deduktiv mantiq / cheklovlar",
      "skill": "Mantiqiy xulosa chiqarish",
      "bloom": "Tahlil",
      "reasoning": "Deduktiv",
      "gradeLevel": "10-sinf",
      "framework": "Cambridge Thinking Skills"
    },
    {
      "id": "Q8",
      "marks": 1,
      "difficulty": "O'rta",
      "strand": "Fazoviy mulohaza",
      "topic": "Fazoviy tasavvur (rasm)",
      "subTopic": "Geometrik / fazoviy",
      "skill": "Fazoviy tasavvur",
      "bloom": "Qo'llash",
      "reasoning": "Fazoviy",
      "gradeLevel": "10-sinf",
      "framework": "Cambridge Thinking Skills"
    },
    {
      "id": "Q9",
      "marks": 1,
      "difficulty": "Qiyin",
      "strand": "Noverbal mulohaza",
      "topic": "Abstrakt matritsa (rasm)",
      "subTopic": "Noverbal / abstrakt mulohaza",
      "skill": "Abstrakt mulohaza",
      "bloom": "Tahlil",
      "reasoning": "Fazoviy",
      "gradeLevel": "10-sinf",
      "framework": "Cambridge Thinking Skills"
    },
    {
      "id": "Q10",
      "marks": 1,
      "difficulty": "O'rta",
      "strand": "Ma'lumotlar tahlili",
      "topic": "Tizimli sanash / kombinatorika",
      "subTopic": "Kombinatorika",
      "skill": "Tizimli sanash",
      "bloom": "Tahlil",
      "reasoning": "Analitik",
      "gradeLevel": "10-sinf",
      "framework": "Cambridge Thinking Skills"
    }
  ]
}